buildbot_prometheus/__init__.py
buildbot_prometheus/prometheus.py
buildbot_prometheus-22.0.0.dist-info/LICENSE
buildbot_prometheus-22.0.0.dist-info/METADATA
buildbot_prometheus-22.0.0.dist-info/WHEEL
buildbot_prometheus-22.0.0.dist-info/entry_points.txt
buildbot_prometheus-22.0.0.dist-info/top_level.txt
buildbot_prometheus-22.0.0.dist-info/RECORD
