Metadata-Version: 2.1
Name: buildbot-prometheus
Version: 22.0.0
Summary: A Prometheus exporter for Buildbot
Home-page: https://github.com/claws/buildbot-prometheus
Author: Chris Laws
Author-email: clawsicus@gmail.com
License: MIT
Keywords: buildbot,prometheus,monitoring,metrics
Platform: UNKNOWN
Classifier: Development Status :: 4 - Beta
Classifier: Intended Audience :: Developers
Classifier: License :: OSI Approved :: MIT License
Classifier: Natural Language :: English
Classifier: Operating System :: OS Independent
Classifier: Programming Language :: Python :: 3.6
Classifier: Programming Language :: Python :: 3.7
Classifier: Programming Language :: Python :: 3.8
Classifier: Programming Language :: Python :: 3.9
Classifier: Programming Language :: Python :: 3.10
Classifier: Topic :: System :: Monitoring
Requires-Python: >=3.6.0
Requires-Dist: buildbot
Requires-Dist: prometheus-client
Requires-Dist: twisted
